[
    {
        "name": "Azerbaijan Grand Prix",
        "year": 2024,
        "youtube": "https://www.youtube.com/watch?v=7ynDOY1PR74&list=PLfoNZDHitwjUv0pjTwlV1vzaE0r7UDVDR&index=1"
    },
    {
        "name": "Italian Grand Prix",
        "year": 2024,
        "youtube": "https://www.youtube.com/watch?v=sTmpbEYUba0&list=PLfoNZDHitwjUv0pjTwlV1vzaE0r7UDVDR&index=2"
    },
    {
        "name": "Dutch Grand Prix",
        "year": 2024,
        "youtube": "https://www.youtube.com/watch?v=cFM_6zb35rI&list=PLfoNZDHitwjUv0pjTwlV1vzaE0r7UDVDR&index=3"
    },
    {
            "name": "Belgian Grand Prix",
            "year": 2024,
            "youtube": "https://www.youtube.com/watch?v=pQaG0ay957M&list=PLfoNZDHitwjUv0pjTwlV1vzaE0r7UDVDR&index=4"
    },
    {
        "name": "Hungarian Grand Prix",
        "year": 2024,
        "youtube": "https://www.youtube.com/watch?v=YJ0NYHONwts&list=PLfoNZDHitwjUv0pjTwlV1vzaE0r7UDVDR&index=5"
    },
    {
        "name": "British Grand Prix",
        "year": 2024,
        "youtube": "https://www.youtube.com/watch?v=yPvoKz6tyJs&list=PLfoNZDHitwjUv0pjTwlV1vzaE0r7UDVDR&index=6"
    },
    {
        "name": "Austrian Grand Prix",
        "year": 2024,
        "youtube": "https://www.youtube.com/watch?v=b0yb1zH2m7c&list=PLfoNZDHitwjUv0pjTwlV1vzaE0r7UDVDR&index=7"
    },
    {
        "name": "Spanish Grand Prix",
        "year": 2024,
        "youtube": "https://www.youtube.com/watch?v=ojUQLuSqV4s&list=PLfoNZDHitwjUv0pjTwlV1vzaE0r7UDVDR&index=8"
    },
    {   
        "name": "Canadian Grand Prix",
        "year": 2024,
        "youtube": "https://www.youtube.com/watch?v=dLw1ao4-Akk&list=PLfoNZDHitwjUv0pjTwlV1vzaE0r7UDVDR&index=9"
    },
    {
        "name": "Monaco Grand Prix",
        "year": 2024,
        "youtube": "https://www.youtube.com/watch?v=aeCI0ObFY8M&list=PLfoNZDHitwjUv0pjTwlV1vzaE0r7UDVDR&index=10"
    },
    {
        "name": "Romagna Grand Prix",
        "year": 2024,
        "youtube": "https://www.youtube.com/watch?v=wya4iAJLlzs&list=PLfoNZDHitwjUv0pjTwlV1vzaE0r7UDVDR&index=11"
    },
    {
        "name": "Miami Grand Prix",
        "year": 2024,
        "youtube": "https://www.youtube.com/watch?v=9wiQqcKUahc&list=PLfoNZDHitwjUv0pjTwlV1vzaE0r7UDVDR&index=12"
    },
    {
        "name": "Chinese Grand Prix",
        "year": 2024,
        "youtube": "https://www.youtube.com/watch?v=hh4prBn66Dc&list=PLfoNZDHitwjUv0pjTwlV1vzaE0r7UDVDR&index=13"
    },
    {
        "name": "Japanese Grand Prix",
        "year": 2024,
        "youtube": "https://www.youtube.com/watch?v=Z3-IulIyBtU&list=PLfoNZDHitwjUv0pjTwlV1vzaE0r7UDVDR&index=14"
    },
    {
        "name": "Australian Grand Prix",
        "year": 2024,
        "youtube": "https://www.youtube.com/watch?v=9z8sEadieXA&list=PLfoNZDHitwjUv0pjTwlV1vzaE0r7UDVDR&index=15"
    },
    {
        "name": "Saudi Arabian Grand Prix",
        "year": 2024,
        "youtube": "https://www.youtube.com/watch?v=OJ56MAGFPGM&list=PLfoNZDHitwjUv0pjTwlV1vzaE0r7UDVDR&index=16"
    }
    ,
    {
        "name": "Bahrain Grand Prix",
        "year": 2024,
        "youtube": "https://www.youtube.com/watch?v=9Y5wMpKXNK4&list=PLfoNZDHitwjUv0pjTwlV1vzaE0r7UDVDR&index=17"
    }


]